{"index" : { "_index" : "c1", "_id" : 1}}
{"metadata_generatedAt": "2021-03-16 17:03:58", "metadata_recordGeneratedBy": "GUA", "metadata_logFileName": "a6fad9ca-9560-477d-ad4c-c37b8c343ec4"}
{"index" : { "_index" : "c1", "_id" : 2}}
{"metadata_generatedAt": "2023-06-13 14:06:21", "metadata_recordGeneratedBy": "PMI", "metadata_logFileName": "2129eb87-fa5e-43a9-b1aa-c6784e11a6fe"}
{"index" : { "_index" : "c1", "_id" : 3}}
{"metadata_generatedAt": "2021-02-10 10:02:11", "metadata_recordGeneratedBy": "BUF", "metadata_logFileName": "ce1ffdf4-ea50-4fa7-a476-bb55017eae5c"}
{"index" : { "_index" : "c1", "_id" : 4}}
{"metadata_generatedAt": "2023-08-26 02:08:53", "metadata_recordGeneratedBy": "TIP", "metadata_logFileName": "1bec94a3-67a8-4712-95f4-cd2a65b1731e"}
{"index" : { "_index" : "c1", "_id" : 5}}
{"metadata_generatedAt": "2023-05-06 06:05:09", "metadata_recordGeneratedBy": "URC", "metadata_logFileName": "52d72bc3-cd85-47d0-b424-2f10827dcbe7"}
{"index" : { "_index" : "c1", "_id" : 6}}
{"metadata_generatedAt": "2023-11-26 09:11:43", "metadata_recordGeneratedBy": "DEN", "metadata_logFileName": "12c2d979-9266-4525-968d-4634737881ea"}
{"index" : { "_index" : "c1", "_id" : 7}}
{"metadata_generatedAt": "2020-10-09 15:10:24", "metadata_recordGeneratedBy": "YNT", "metadata_logFileName": "1b13dfc0-5510-4103-b1a3-db63d20077e6"}
{"index" : { "_index" : "c1", "_id" : 8}}
{"metadata_generatedAt": "2021-06-14 19:06:08", "metadata_recordGeneratedBy": "SKT", "metadata_logFileName": "9ab5ce97-31a3-4eba-a801-1c5bd8cf0be9"}
{"index" : { "_index" : "c1", "_id" : 9}}
{"metadata_generatedAt": "2020-01-18 18:01:49", "metadata_recordGeneratedBy": "EIN", "metadata_logFileName": "af6046cb-34f3-4b5e-9587-0e578796f234"}
{"index" : { "_index" : "c1", "_id" : 10}}
{"metadata_generatedAt": "2021-09-01 09:09:06", "metadata_recordGeneratedBy": "MRU", "metadata_logFileName": "f9ce80c5-fc1c-4c3a-a6be-b8ed771be8df"}
{"index" : { "_index" : "c1", "_id" : 11}}
{"metadata_generatedAt": "2021-11-06 05:11:37", "metadata_recordGeneratedBy": "YEG", "metadata_logFileName": "1b0707c2-4ddf-4943-ae10-706d2b2b127d"}
{"index" : { "_index" : "c1", "_id" : 12}}
{"metadata_generatedAt": "2022-09-08 13:09:02", "metadata_recordGeneratedBy": "RAR", "metadata_logFileName": "2200443f-87e2-4f87-af12-3b7c01f70048"}
{"index" : { "_index" : "c1", "_id" : 13}}
{"metadata_generatedAt": "2021-01-30 10:01:45", "metadata_recordGeneratedBy": "CPT", "metadata_logFileName": "7aa3dbf1-6a61-48a4-b4ee-6e3f3de685a9"}
{"index" : { "_index" : "c1", "_id" : 14}}
{"metadata_generatedAt": "2023-04-29 00:04:55", "metadata_recordGeneratedBy": "DUB", "metadata_logFileName": "782bef19-7559-404f-9a72-cec581248017"}
{"index" : { "_index" : "c1", "_id" : 15}}
{"metadata_generatedAt": "2023-12-23 19:12:25", "metadata_recordGeneratedBy": "TSE", "metadata_logFileName": "46a2b280-9879-48a9-8645-2ecb41df4adc"}
{"index" : { "_index" : "c1", "_id" : 16}}
{"metadata_generatedAt": "2020-07-26 02:07:43", "metadata_recordGeneratedBy": "SHO", "metadata_logFileName": "c1ceec24-7713-43d0-b866-587b79b42788"}
{"index" : { "_index" : "c1", "_id" : 17}}
{"metadata_generatedAt": "2022-06-13 08:06:46", "metadata_recordGeneratedBy": "SLC", "metadata_logFileName": "a1b51c7b-cf63-4992-a9aa-2529f905d39f"}
{"index" : { "_index" : "c1", "_id" : 18}}
{"metadata_generatedAt": "2023-09-02 23:09:21", "metadata_recordGeneratedBy": "EMA", "metadata_logFileName": "a8e48c0b-22f7-4297-a312-1c5c3e9a2458"}
{"index" : { "_index" : "c1", "_id" : 19}}
{"metadata_generatedAt": "2023-01-01 05:01:26", "metadata_recordGeneratedBy": "SAV", "metadata_logFileName": "e1cf8592-86f8-4b91-a4fb-fa38557a1b42"}
{"index" : { "_index" : "c1", "_id" : 20}}
{"metadata_generatedAt": "2020-06-09 00:06:20", "metadata_recordGeneratedBy": "GYD", "metadata_logFileName": "9737af4a-6b71-4ac5-9be7-3596e98dc818"}
{"index" : { "_index" : "c1", "_id" : 21}}
{"metadata_generatedAt": "2023-07-19 12:07:36", "metadata_recordGeneratedBy": "BGW", "metadata_logFileName": "91748ca2-e0d3-4c7e-a1d2-12ded409f88c"}
{"index" : { "_index" : "c1", "_id" : 22}}
{"metadata_generatedAt": "2022-01-14 11:01:25", "metadata_recordGeneratedBy": "MRU", "metadata_logFileName": "bc88c945-185e-41b4-ab57-1f740950c795"}
{"index" : { "_index" : "c1", "_id" : 23}}
{"metadata_generatedAt": "2022-06-24 01:06:36", "metadata_recordGeneratedBy": "NIM", "metadata_logFileName": "b9ee2fa7-3fb3-44e7-ae82-551e559a44e4"}
{"index" : { "_index" : "c1", "_id" : 24}}
{"metadata_generatedAt": "2021-04-15 11:04:20", "metadata_recordGeneratedBy": "SXM", "metadata_logFileName": "fd449b6f-673a-4e5d-84a0-dc06c95b0dd9"}
{"index" : { "_index" : "c1", "_id" : 25}}
{"metadata_generatedAt": "2023-02-27 05:02:04", "metadata_recordGeneratedBy": "ROA", "metadata_logFileName": "38159eca-ef96-42f8-86dc-626f5560f0c5"}
{"index" : { "_index" : "c1", "_id" : 26}}
{"metadata_generatedAt": "2023-03-15 02:03:10", "metadata_recordGeneratedBy": "NDJ", "metadata_logFileName": "f9abfae1-e7de-4388-8857-255da8d17594"}
{"index" : { "_index" : "c1", "_id" : 27}}
{"metadata_generatedAt": "2020-07-18 18:07:19", "metadata_recordGeneratedBy": "CVS", "metadata_logFileName": "39b9b219-90a7-4572-8bae-64a195ffe595"}
{"index" : { "_index" : "c1", "_id" : 28}}
{"metadata_generatedAt": "2023-02-27 18:02:46", "metadata_recordGeneratedBy": "ACA", "metadata_logFileName": "f5a41dd3-1c0a-499c-9706-c1bb2e07fe5d"}
{"index" : { "_index" : "c1", "_id" : 29}}
{"metadata_generatedAt": "2022-01-13 00:01:07", "metadata_recordGeneratedBy": "BHX", "metadata_logFileName": "e1d8579c-5d89-45d8-b40e-06797a52ba63"}
{"index" : { "_index" : "c1", "_id" : 30}}
{"metadata_generatedAt": "2021-01-20 19:01:48", "metadata_recordGeneratedBy": "NWI", "metadata_logFileName": "af135d49-c815-4b45-8cc9-b39c5102731b"}
{"index" : { "_index" : "c1", "_id" : 31}}
{"metadata_generatedAt": "2022-05-20 10:05:22", "metadata_recordGeneratedBy": "SSA", "metadata_logFileName": "d471172e-da15-4daf-a777-97df5ef7b22e"}
{"index" : { "_index" : "c1", "_id" : 32}}
{"metadata_generatedAt": "2023-03-30 07:03:25", "metadata_recordGeneratedBy": "DME", "metadata_logFileName": "82a9bc6a-59ae-49d2-8aba-cb460a47977f"}
{"index" : { "_index" : "c1", "_id" : 33}}
{"metadata_generatedAt": "2022-01-25 18:01:07", "metadata_recordGeneratedBy": "SIP", "metadata_logFileName": "7ff7dffd-7c3a-43f4-97ef-319227002118"}
{"index" : { "_index" : "c1", "_id" : 34}}
{"metadata_generatedAt": "2020-02-15 02:02:24", "metadata_recordGeneratedBy": "KWL", "metadata_logFileName": "035f542d-6d2e-40ec-9e33-bdf0e95879a8"}
{"index" : { "_index" : "c1", "_id" : 35}}
{"metadata_generatedAt": "2021-12-31 13:12:26", "metadata_recordGeneratedBy": "GZT", "metadata_logFileName": "fdc07cbe-7ce9-4b12-ad70-a1b08e079680"}
{"index" : { "_index" : "c1", "_id" : 36}}
{"metadata_generatedAt": "2022-01-22 22:01:25", "metadata_recordGeneratedBy": "YYJ", "metadata_logFileName": "1f4f1088-9770-4749-ab4f-61c0fc73c564"}
{"index" : { "_index" : "c1", "_id" : 37}}
{"metadata_generatedAt": "2022-03-21 08:03:58", "metadata_recordGeneratedBy": "SYR", "metadata_logFileName": "0eee87f0-9a47-4cd0-a0b5-6100257a555b"}
{"index" : { "_index" : "c1", "_id" : 38}}
{"metadata_generatedAt": "2021-08-22 01:08:37", "metadata_recordGeneratedBy": "ZAG", "metadata_logFileName": "3d7467ea-c62e-440c-b071-b917451f1736"}
{"index" : { "_index" : "c1", "_id" : 39}}
{"metadata_generatedAt": "2023-08-09 03:08:05", "metadata_recordGeneratedBy": "MLA", "metadata_logFileName": "ca7a10e7-d2d9-428d-b522-fc2297d8d75b"}
{"index" : { "_index" : "c1", "_id" : 40}}
{"metadata_generatedAt": "2023-05-26 19:05:58", "metadata_recordGeneratedBy": "AYT", "metadata_logFileName": "e1966c97-3dae-41cb-af65-b531813fe742"}
{"index" : { "_index" : "c1", "_id" : 41}}
{"metadata_generatedAt": "2022-01-25 23:01:18", "metadata_recordGeneratedBy": "QUO", "metadata_logFileName": "81d6a736-e04d-4bf3-8c35-a7fe003ea819"}
{"index" : { "_index" : "c1", "_id" : 42}}
{"metadata_generatedAt": "2022-12-21 09:12:56", "metadata_recordGeneratedBy": "THR", "metadata_logFileName": "57f503e4-7b30-410e-a92d-8790873f9974"}
{"index" : { "_index" : "c1", "_id" : 43}}
{"metadata_generatedAt": "2023-08-06 09:08:41", "metadata_recordGeneratedBy": "ACA", "metadata_logFileName": "74329682-3a47-4969-a4c2-5cb3cb019c20"}
{"index" : { "_index" : "c1", "_id" : 44}}
{"metadata_generatedAt": "2021-07-17 13:07:16", "metadata_recordGeneratedBy": "DLM", "metadata_logFileName": "7f110ca8-9881-48db-99f8-096da92fd4e1"}
{"index" : { "_index" : "c1", "_id" : 45}}
{"metadata_generatedAt": "2022-04-13 00:04:40", "metadata_recordGeneratedBy": "TRN", "metadata_logFileName": "567598a4-3bf7-4ad7-9109-cec26b454ef3"}
{"index" : { "_index" : "c1", "_id" : 46}}
{"metadata_generatedAt": "2020-02-16 15:02:35", "metadata_recordGeneratedBy": "RST", "metadata_logFileName": "293b2c35-b9b1-4cdc-9b47-0f8563ea6c9a"}
{"index" : { "_index" : "c1", "_id" : 47}}
{"metadata_generatedAt": "2023-03-09 18:03:55", "metadata_recordGeneratedBy": "PRG", "metadata_logFileName": "1b5aeb98-868e-4be6-b314-991c2ad633ef"}
{"index" : { "_index" : "c1", "_id" : 48}}
{"metadata_generatedAt": "2020-05-05 05:05:44", "metadata_recordGeneratedBy": "MSP", "metadata_logFileName": "93c749de-df0b-4e74-9853-34d3291d01d3"}
{"index" : { "_index" : "c1", "_id" : 49}}
{"metadata_generatedAt": "2021-02-17 08:02:24", "metadata_recordGeneratedBy": "FRA", "metadata_logFileName": "305e708e-88b1-4ea0-a8e7-33acfc3c9d06"}
{"index" : { "_index" : "c1", "_id" : 50}}
{"metadata_generatedAt": "2022-12-25 12:12:54", "metadata_recordGeneratedBy": "MCF", "metadata_logFileName": "d7b91fef-cdec-468e-87db-d39f8b2ed3b2"}
{"index" : { "_index" : "c1", "_id" : 51}}
{"metadata_generatedAt": "2020-08-20 07:08:25", "metadata_recordGeneratedBy": "KTM", "metadata_logFileName": "ef186b7f-9e7b-45cd-95b0-fd7500114c44"}
{"index" : { "_index" : "c1", "_id" : 52}}
{"metadata_generatedAt": "2020-07-31 20:07:19", "metadata_recordGeneratedBy": "CAG", "metadata_logFileName": "fda31c0c-c3e9-47e4-a152-58ff3a430038"}
{"index" : { "_index" : "c1", "_id" : 53}}
{"metadata_generatedAt": "2020-02-06 21:02:17", "metadata_recordGeneratedBy": "BOJ", "metadata_logFileName": "31b705a4-acc4-4fed-ab92-c08bf460f323"}
{"index" : { "_index" : "c1", "_id" : 54}}
{"metadata_generatedAt": "2022-06-02 10:06:24", "metadata_recordGeneratedBy": "CNX", "metadata_logFileName": "de93dbb8-c4b4-4c20-bd42-944131df2833"}
{"index" : { "_index" : "c1", "_id" : 55}}
{"metadata_generatedAt": "2020-06-12 02:06:31", "metadata_recordGeneratedBy": "DMM", "metadata_logFileName": "ec51166e-1cca-44a9-81ce-8334ba3e04a0"}
{"index" : { "_index" : "c1", "_id" : 56}}
{"metadata_generatedAt": "2021-02-06 17:02:19", "metadata_recordGeneratedBy": "HAK", "metadata_logFileName": "029a6e90-c261-4feb-83bc-4970913754d2"}
{"index" : { "_index" : "c1", "_id" : 57}}
{"metadata_generatedAt": "2021-07-15 01:07:25", "metadata_recordGeneratedBy": "BGO", "metadata_logFileName": "66e50b98-0516-447e-a9a0-4d87d8d2decf"}
{"index" : { "_index" : "c1", "_id" : 58}}
{"metadata_generatedAt": "2020-03-23 20:03:51", "metadata_recordGeneratedBy": "GRV", "metadata_logFileName": "a81bae2a-2e1c-42d8-be9d-7e757059d69f"}
{"index" : { "_index" : "c1", "_id" : 59}}
{"metadata_generatedAt": "2022-04-22 00:04:35", "metadata_recordGeneratedBy": "TGD", "metadata_logFileName": "63aa14f7-8755-468c-8f85-00d5b8a28dc1"}
{"index" : { "_index" : "c1", "_id" : 60}}
{"metadata_generatedAt": "2021-08-19 17:08:23", "metadata_recordGeneratedBy": "JAN", "metadata_logFileName": "edda713b-3d95-451a-bf8f-f3557584394f"}
{"index" : { "_index" : "c1", "_id" : 61}}
{"metadata_generatedAt": "2023-06-11 18:06:48", "metadata_recordGeneratedBy": "SJD", "metadata_logFileName": "f1384260-2055-4772-a448-51ac41106797"}
{"index" : { "_index" : "c1", "_id" : 62}}
{"metadata_generatedAt": "2022-06-28 05:06:01", "metadata_recordGeneratedBy": "CBR", "metadata_logFileName": "e9d69b37-d5c0-4c2a-9fd2-5c3a65c9f150"}
{"index" : { "_index" : "c1", "_id" : 63}}
{"metadata_generatedAt": "2021-10-17 14:10:46", "metadata_recordGeneratedBy": "PNH", "metadata_logFileName": "ba562c20-d93e-49d7-a91e-4d752bd612d4"}
{"index" : { "_index" : "c1", "_id" : 64}}
{"metadata_generatedAt": "2021-12-16 07:12:03", "metadata_recordGeneratedBy": "EDI", "metadata_logFileName": "bb4d8fe8-8532-4c78-b1db-2a1046a64a7c"}
{"index" : { "_index" : "c1", "_id" : 65}}
{"metadata_generatedAt": "2021-08-31 15:08:51", "metadata_recordGeneratedBy": "TPE", "metadata_logFileName": "5361abb9-7935-4a40-a35e-995e0bad9ce9"}
{"index" : { "_index" : "c1", "_id" : 66}}
{"metadata_generatedAt": "2021-04-29 15:04:15", "metadata_recordGeneratedBy": "MEX", "metadata_logFileName": "75da62b0-fe51-4f9e-9133-b86796001f76"}
{"index" : { "_index" : "c1", "_id" : 67}}
{"metadata_generatedAt": "2022-02-03 11:02:23", "metadata_recordGeneratedBy": "CCS", "metadata_logFileName": "03b03581-1f80-46fe-bcd6-f18016eff9ff"}
{"index" : { "_index" : "c1", "_id" : 68}}
{"metadata_generatedAt": "2023-05-15 13:05:04", "metadata_recordGeneratedBy": "HOU", "metadata_logFileName": "f41e6405-80f1-416d-90ce-b7ee69b9df35"}
{"index" : { "_index" : "c1", "_id" : 69}}
{"metadata_generatedAt": "2021-11-02 12:11:10", "metadata_recordGeneratedBy": "POM", "metadata_logFileName": "50256216-903d-403b-bb31-f5acec950604"}
{"index" : { "_index" : "c1", "_id" : 70}}
{"metadata_generatedAt": "2022-11-07 11:11:18", "metadata_recordGeneratedBy": "", "metadata_logFileName": "8a20f567-e596-4eb2-a584-a56cfefdf5ea"}
{"index" : { "_index" : "c1", "_id" : 71}}
{"metadata_generatedAt": "2020-04-30 11:04:56", "metadata_recordGeneratedBy": "HGH", "metadata_logFileName": "24fd0bed-03bd-46da-b5ec-01dc26d74a2c"}
{"index" : { "_index" : "c1", "_id" : 72}}
{"metadata_generatedAt": "2021-08-28 01:08:41", "metadata_recordGeneratedBy": "CMH", "metadata_logFileName": "a9681a03-6939-4dd0-847c-264aa2aaf17f"}
{"index" : { "_index" : "c1", "_id" : 73}}
{"metadata_generatedAt": "2021-12-05 08:12:20", "metadata_recordGeneratedBy": "STR", "metadata_logFileName": "b570b22c-6f2f-48df-bf77-77ff2dcbf868"}
{"index" : { "_index" : "c1", "_id" : 74}}
{"metadata_generatedAt": "2020-10-04 01:10:57", "metadata_recordGeneratedBy": "ISL", "metadata_logFileName": "5067fc09-ac9c-494d-9a00-ad829ea87270"}
{"index" : { "_index" : "c1", "_id" : 75}}
{"metadata_generatedAt": "2023-02-15 23:02:23", "metadata_recordGeneratedBy": "ASB", "metadata_logFileName": "4b0a1edf-e5bf-4180-b2bb-7ce3a92bdfd9"}
{"index" : { "_index" : "c1", "_id" : 76}}
{"metadata_generatedAt": "2023-02-12 18:02:38", "metadata_recordGeneratedBy": "CMB", "metadata_logFileName": "440fdf26-7c62-49fa-99d3-889eee3114ec"}
{"index" : { "_index" : "c1", "_id" : 77}}
{"metadata_generatedAt": "2021-06-14 14:06:25", "metadata_recordGeneratedBy": "MSY", "metadata_logFileName": "3e1bd74f-2eaf-4058-a888-93b6c3141e54"}
{"index" : { "_index" : "c1", "_id" : 78}}
{"metadata_generatedAt": "2020-05-31 01:05:58", "metadata_recordGeneratedBy": "ORK", "metadata_logFileName": "abd6df52-b62f-4a0a-a4f8-50a6c725a9b9"}
{"index" : { "_index" : "c1", "_id" : 79}}
{"metadata_generatedAt": "2023-03-27 08:03:42", "metadata_recordGeneratedBy": "PSA", "metadata_logFileName": "8a2ab7a6-5e7b-4e60-b5d2-6b498bab9c30"}
{"index" : { "_index" : "c1", "_id" : 80}}
{"metadata_generatedAt": "2020-01-04 11:01:54", "metadata_recordGeneratedBy": "ABQ", "metadata_logFileName": "2eb79cb8-cab9-4dc3-965b-8eb766945a32"}
{"index" : { "_index" : "c1", "_id" : 81}}
{"metadata_generatedAt": "2021-03-06 15:03:56", "metadata_recordGeneratedBy": "", "metadata_logFileName": "36caac4c-0549-4bfb-8ded-daafa99d50ae"}
{"index" : { "_index" : "c1", "_id" : 82}}
{"metadata_generatedAt": "2023-07-31 21:07:42", "metadata_recordGeneratedBy": "MGE", "metadata_logFileName": "a40c6336-f149-4bc1-a55c-bf40ffc22dfc"}
{"index" : { "_index" : "c1", "_id" : 83}}
{"metadata_generatedAt": "2020-12-10 17:12:38", "metadata_recordGeneratedBy": "PNH", "metadata_logFileName": "101cde7e-2ed5-44f9-9371-4cfe07a8aab8"}
{"index" : { "_index" : "c1", "_id" : 84}}
{"metadata_generatedAt": "2020-06-18 12:06:17", "metadata_recordGeneratedBy": "ULN", "metadata_logFileName": "6620edbb-a415-4f62-a636-0b1003eb18f3"}
{"index" : { "_index" : "c1", "_id" : 85}}
{"metadata_generatedAt": "2022-09-11 02:09:05", "metadata_recordGeneratedBy": "BOO", "metadata_logFileName": "5915a318-00b1-4eb6-85db-ab0896be712c"}
{"index" : { "_index" : "c1", "_id" : 86}}
{"metadata_generatedAt": "2020-10-20 07:10:32", "metadata_recordGeneratedBy": "ABZ", "metadata_logFileName": "ea645863-5b02-41aa-978d-b644a607ad35"}
{"index" : { "_index" : "c1", "_id" : 87}}
{"metadata_generatedAt": "2020-07-21 02:07:00", "metadata_recordGeneratedBy": "CLT", "metadata_logFileName": "4ee1bd52-af6e-47c8-976e-b75524287d74"}
{"index" : { "_index" : "c1", "_id" : 88}}
{"metadata_generatedAt": "2023-03-31 03:03:09", "metadata_recordGeneratedBy": "MAO", "metadata_logFileName": "8fca9531-6d74-437e-ac07-5d6cf2b854e4"}
{"index" : { "_index" : "c1", "_id" : 89}}
{"metadata_generatedAt": "2022-03-30 17:03:17", "metadata_recordGeneratedBy": "GUS", "metadata_logFileName": "56a0a20a-4946-4bcb-a0a8-7a454c3e83aa"}
{"index" : { "_index" : "c1", "_id" : 90}}
{"metadata_generatedAt": "2022-01-03 17:01:13", "metadata_recordGeneratedBy": "TBS", "metadata_logFileName": "c3e6e134-6eae-4fc0-98a4-e4be72b3d5f8"}
{"index" : { "_index" : "c1", "_id" : 91}}
{"metadata_generatedAt": "2020-10-24 15:10:04", "metadata_recordGeneratedBy": "PDL", "metadata_logFileName": "2d65a87e-15af-49b5-b079-ee6486d92290"}
{"index" : { "_index" : "c1", "_id" : 92}}
{"metadata_generatedAt": "2022-07-08 00:07:13", "metadata_recordGeneratedBy": "DWC", "metadata_logFileName": "dfa3b949-729a-4a43-96d5-d48df974a39b"}
{"index" : { "_index" : "c1", "_id" : 93}}
{"metadata_generatedAt": "2021-04-03 18:04:16", "metadata_recordGeneratedBy": "BLV", "metadata_logFileName": "3dda1be8-b61f-4833-b950-9c824fa92647"}
{"index" : { "_index" : "c1", "_id" : 94}}
{"metadata_generatedAt": "2021-10-06 09:10:34", "metadata_recordGeneratedBy": "TFN", "metadata_logFileName": "a082aff2-c618-49f7-9eab-a9b0755e0ded"}
{"index" : { "_index" : "c1", "_id" : 95}}
{"metadata_generatedAt": "2021-07-18 07:07:30", "metadata_recordGeneratedBy": "AAL", "metadata_logFileName": "65c9f5b9-6ced-4b39-a6cf-49cd8442c5dd"}
{"index" : { "_index" : "c1", "_id" : 96}}
{"metadata_generatedAt": "2020-02-10 06:02:37", "metadata_recordGeneratedBy": "TBZ", "metadata_logFileName": "772ad72e-7115-48cd-9cbd-bc6fc6f3e651"}
{"index" : { "_index" : "c1", "_id" : 97}}
{"metadata_generatedAt": "2022-04-30 01:04:40", "metadata_recordGeneratedBy": "ROV", "metadata_logFileName": "8ec4ea29-6db5-47ca-a9a2-01b9d756e6c3"}
{"index" : { "_index" : "c1", "_id" : 98}}
{"metadata_generatedAt": "2020-06-04 18:06:37", "metadata_recordGeneratedBy": "END", "metadata_logFileName": "b348bcc9-d5cb-4157-83e6-214630c5806d"}
{"index" : { "_index" : "c1", "_id" : 99}}
{"metadata_generatedAt": "2022-11-02 13:11:22", "metadata_recordGeneratedBy": "LTS", "metadata_logFileName": "91578f8e-962c-4507-b6c5-d41eb3405043"}
